porthole/TimeHelper.py
porthole/__init__.py
porthole/alerts.py
porthole/app.py
porthole/components.py
porthole/connections.py
porthole/contact_management.py
porthole/filters.py
porthole/formats.py
porthole/getting_started.py
porthole/logger.py
porthole/mailer.py
porthole/models.py
porthole/queries.py
porthole/related_record.py
porthole/reports.py
porthole/result_containers.py
porthole/tasks.py
porthole/uploaders.py
porthole/workflows.py
porthole/xlsx.py
porthole-0.8.5.dist-info/LICENSE
porthole-0.8.5.dist-info/METADATA
porthole-0.8.5.dist-info/WHEEL
porthole-0.8.5.dist-info/top_level.txt
porthole-0.8.5.dist-info/RECORD
