Metadata-Version: 2.1
Name: porthole
Version: 0.8.5
Summary: An automated reporting package.
Home-page: https://github.com/speedyturkey/porthole
Author: Billy McMonagle
Author-email: speedyturkey@gmail.com
License: UNKNOWN
Platform: UNKNOWN
Requires-Python: >3.6
Requires-Dist: openpyxl
Requires-Dist: psycopg2-binary
Requires-Dist: pymysql
Requires-Dist: pytz
Requires-Dist: SQLAlchemy
Requires-Dist: xlsxwriter
Provides-Extra: aws
Requires-Dist: boto3 ; extra == 'aws'
